configuration/__init__.py
configuration/configuration.py
bn_configuration-0.0.5.dist-info/METADATA
bn_configuration-0.0.5.dist-info/WHEEL
bn_configuration-0.0.5.dist-info/top_level.txt
bn_configuration-0.0.5.dist-info/RECORD
